queryeasy.py
queryeasy-0.0.4.dist-info/LICENSE
queryeasy-0.0.4.dist-info/METADATA
queryeasy-0.0.4.dist-info/WHEEL
queryeasy-0.0.4.dist-info/entry_points.txt
queryeasy-0.0.4.dist-info/top_level.txt
queryeasy-0.0.4.dist-info/RECORD
