Metadata-Version: 2.1
Name: queryeasy
Version: 0.0.4
Summary: Execute SQL queries on data present in CSV or Excel files. Also allows to generate the query output files.
Home-page: https://github.com/dheerajalim/queryeasy
Author: Dheeraj Alimchandani
Author-email: dheeraj.alim@gmail.com
License: UNKNOWN
Project-URL: Bug Tracker, https://github.com/dheerajalim/queryeasy/issues
Platform: UNKNOWN
Classifier: Development Status :: 4 - Beta
Classifier: Programming Language :: Python :: 3
Classifier: Programming Language :: Python :: 3.6
Classifier: Programming Language :: Python :: 3.7
Classifier: Programming Language :: Python :: 3.8
Classifier: License :: OSI Approved :: MIT License
Classifier: Operating System :: OS Independent
Classifier: Topic :: Software Development :: Libraries
Classifier: Topic :: Desktop Environment
Classifier: Environment :: Console
Requires-Python: >=3.6
Requires-Dist: pandas (~=1.2)
Requires-Dist: xlrd (==1.2.0)
Requires-Dist: xlwt (==1.2.0)
Requires-Dist: openpyxl (~=3.0)
Requires-Dist: sqlalchemy (~=1.4)
